Metadata-Version: 1.0
Name: sholz-distributions
Version: 0.1
Summary: Gaussian distributions
Home-page: UNKNOWN
Author: Solamipe Akinola
Author-email: UNKNOWN
License: UNKNOWN
Platform: UNKNOWN
